[{"line":1,"elements":[{"start_timestamp":"2022-06-17T12:05:22.298Z","before":[{"result":{"duration":1997300,"status":"passed"},"match":{"location":"stepdefinitions.Hooks.setUp()"}}],"line":4,"name":"TC01_Amazon Search Testi","description":"","id":"us1001-amazonsearch;tc01-amazon-search-testi","after":[{"result":{"duration":2002615400,"status":"passed"},"match":{"location":"stepdefinitions.Hooks.tearDown(io.cucumber.java.Scenario)"}}],"type":"scenario","keyword":"Scenario","steps":[{"result":{"duration":12175314200,"status":"passed"},"line":5,"name":"kullanici amazon sayfasina gider","match":{"location":"stepdefinitions.AmazonStepDefinitions.kullanici_amazon_sayfasina_gider()"},"keyword":"Given "},{"result":{"duration":4220783200,"status":"passed"},"line":6,"name":"iPhone icin arama yapar","match":{"location":"stepdefinitions.AmazonStepDefinitions.i_phone_icin_arama_yapar()"},"keyword":"And "},{"result":{"duration":70912100,"status":"passed"},"line":7,"name":"sonuclarin iPhone icerdigini test eder","match":{"location":"stepdefinitions.AmazonStepDefinitions.sonuclarin_iPhone_icerdigini_test_eder()"},"keyword":"Then "},{"result":{"duration":1617390600,"status":"passed"},"line":9,"name":"kullanici amazon sayfasina gider","match":{"location":"stepdefinitions.AmazonStepDefinitions.kullanici_amazon_sayfasina_gider()"},"keyword":"Given "},{"result":{"duration":4842501200,"status":"passed"},"line":10,"name":"tea pot icin arama yapar","match":{"location":"stepdefinitions.AmazonStepDefinitions.tea_pot_icin_arama_yapar()"},"keyword":"And "},{"result":{"duration":57862200,"status":"passed"},"line":11,"name":"sonuclarin tea pot icerdigini test eder","match":{"location":"stepdefinitions.AmazonStepDefinitions.sonuclarin_tea_pot_icerdigini_test_eder()"},"keyword":"Then "},{"result":{"duration":1446059100,"status":"passed"},"line":13,"name":"kullanici amazon sayfasina gider","match":{"location":"stepdefinitions.AmazonStepDefinitions.kullanici_amazon_sayfasina_gider()"},"keyword":"Given "},{"result":{"duration":3861808300,"status":"passed"},"line":14,"name":"flower icin arama yapar","match":{"location":"stepdefinitions.AmazonStepDefinitions.flower_icin_arama_yapar()"},"keyword":"And "},{"result":{"duration":54970700,"status":"passed"},"line":15,"name":"sonuclarin flower icerdigini test eder","match":{"location":"stepdefinitions.AmazonStepDefinitions.sonuclarin_flower_icerdigini_test_eder()"},"keyword":"Then "}],"tags":[{"name":"@toplu"},{"name":"@paralel1"}]}],"name":"US1001_amazonsearch","description":"","id":"us1001-amazonsearch","keyword":"Feature","uri":"file:src/test/resources/features/US1001_amazonsearch.feature","tags":[]},{"line":2,"elements":[{"start_timestamp":"2022-06-17T12:05:52.751Z","before":[{"result":{"duration":11990500,"status":"passed"},"match":{"location":"stepdefinitions.Hooks.setUp()"}}],"line":4,"name":"TC05_parametre kullanimi","description":"","id":"us1003-parametre-ile-stepdefinition-olusturma;tc05-parametre-kullanimi","after":[{"result":{"duration":3738645300,"status":"passed"},"match":{"location":"stepdefinitions.Hooks.tearDown(io.cucumber.java.Scenario)"}}],"type":"scenario","keyword":"Scenario","steps":[{"result":{"duration":7861474500,"status":"passed"},"line":6,"name":"kullanici amazon sayfasina gider","match":{"location":"stepdefinitions.AmazonStepDefinitions.kullanici_amazon_sayfasina_gider()"},"keyword":"Given "},{"result":{"duration":5590798600,"status":"passed"},"line":7,"name":"\"Java\" icin arama yapar","match":{"arguments":[{"val":"\"Java\"","offset":0}],"location":"stepdefinitions.AmazonStepDefinitions.icin_arama_yapar(java.lang.String)"},"keyword":"And "},{"result":{"duration":80951300,"status":"passed"},"line":8,"name":"sonuclarin \"Java\" icerdigini test eder","match":{"arguments":[{"val":"\"Java\"","offset":11}],"location":"stepdefinitions.AmazonStepDefinitions.sonuclarin_icerdigini_test_eder(java.lang.String)"},"keyword":"Then "},{"result":{"duration":771561800,"status":"passed"},"line":9,"name":"sayfayi kapatir","match":{"location":"stepdefinitions.HotelMyCampStepDefinitions.sayfayiKapatir()"},"keyword":"And "}],"tags":[{"name":"@parametreliTest"},{"name":"@toplu"},{"name":"@paralel1"}]}],"name":"US1003 parametre ile stepdefinition olusturma","description":"","id":"us1003-parametre-ile-stepdefinition-olusturma","keyword":"Feature","uri":"file:src/test/resources/features/US1003_ParametreKullanimi.feature","tags":[{"name":"@parametreliTest","type":"Tag","location":{"line":1,"column":1}}]}]